README.md
setup.py
dogebuild/__init__.py
dogebuild/common.py
dogebuild/controller.py
dogebuild/dependencies_functions.py
dogebuild/dogebuild.version
dogebuild/dogefile.py
dogebuild/plugins.py
dogebuild/tools.py
dogebuild/well_known_artifacts.py
dogebuild.egg-info/PKG-INFO
dogebuild.egg-info/SOURCES.txt
dogebuild.egg-info/dependency_links.txt
dogebuild.egg-info/entry_points.txt
dogebuild.egg-info/requires.txt
dogebuild.egg-info/top_level.txt
dogebuild/dogefile_internals/__init__.py
dogebuild/dogefile_internals/context.py
dogebuild/dogefile_internals/decorators.py
dogebuild/dogefile_internals/dependencies.py
dogebuild/dogefile_internals/errors.py
dogebuild/dogefile_internals/modules.py
dogebuild/dogefile_internals/parameters.py
dogebuild/dogefile_internals/relations.py
scripts/doge_runner.py